[{},{"bxlatenea":[929],"bxuotlyn":[2262],"bxtowyn":[4254,4592,4955],"bxaarrjaaaa":[58039],"bxtirovaiv":[58039],"bxp":[58039],"bxeirere":[58039],"bxr":[58039],"bxfltfl":[58039],"bxdovs":[58039],"bxeirei":[58039],"bxov":[58061],"bxtos":[58061]},{"bxpiess":[1062],"bxitaix":[2036],"bxz":[2164],"bxokavttitpara":[58039],"bxetlrev":[58039],"bxe":[58039],"bxlyov":[58039],"bxovs":[58039],"bxcmov":[58061]},{"bxooklyn":[714],"bxiuch":[1020],"bxrber":[1021],"bxubek":[1064],"bxrbeii":[1071],"bxitish":[1131],"bxiov":[58039],"bxov":[58039],"bxi":[58061]},{"bxhaih":[929],"bxrj":[58039],"bxereaiv":[58039],"bxqgev":[58039],"bxqgqar":[58039],"bxqgrj":[58039],"bxqpevqv":[58039],"bxqgetap":[58039],"bxqgqvai":[58039],"bxqgqri":[58039],"bxi":[58039],"bxrt0ijvai":[58039],"bxrjreov":[58039],"bxrjgels":[58039],"bxerrere":[58039],"bxdaroi":[58039],"bxrjv":[58061],"bxp":[58061],"bxpv":[58061]},{"bxaarov":[58039],"bxaa":[58039],"bxaatjirjplav":[58039],"bxaarpqplas":[58039],"bxaaipqplas":[58039],"bxaarfrrjpias":[58039],"bxeppan":[58039],"bxena":[58039],"bxenaiv":[58039],"bxenarv":[58039],"bxencov":[58039],"bxeneis":[58039],"bxeneiv":[58039],"bxenovres":[58039],"bxenovaiv":[58039],"bxenere":[58039],"bxenav":[58039],"bxenovras":[58039],"bxenaiaiv":[58039],"bxenei":[58039],"bxenopev":[58039],"bxenovra":[58039],"bxenopevrj":[58039],"bxenera":[58039],"bxetreis":[58039],"bxttrwv":[58039],"bxxos":[58039],"bxrjv":[58039],"bxiyov":[58039],"bxw":[58039],"bxeireis":[58061]},{"bxejropev":[58039],"bxxovs":[58039],"bxps":[58039],"bxiyfstais":[58039],"bxiyfns":[58039],"bxgttgtg":[58061],"bxetrere":[58061],"bxu":[58291]},{"bxaar":[58039],"bxcos":[58039],"bxys":[58061],"bxeif":[58061],"bxrj":[58061]},{"bxiif":[2519],"bxtyoi":[58039],"bxlyois":[58039],"bxxoi":[58039],"bxav":[58061],"bxodus":[58122]},{"bxeca":[1130],"bxeylras":[58039],"bxaoroi":[58039],"bxeiraatv":[58039],"bxiyot":[58039],"bxiyoi":[58039],"bxlyoi":[58039],"bxn":[58325]},{"bxdarov":[58039],"bxxov":[58039],"bxatr":[58061]},{"bxqv":[58039],"bxqs":[58039],"bxiyois":[58039],"bxokavrwpara":[58039],"bxeirei":[58061],"bxos":[58061]},{"bxooklyu":[591],"bxtya":[58039],"bxlyps":[58039],"bxa":[58039],"bxve":[58061]},{"bxavcly":[935],"bxlyof":[58039],"bxo0pev":[58039],"bxdiqivn":[58039],"bxaatjnjptav":[58039]},{"bxirrei":[58039],"bxtp":[58061]},{"bxlyai":[58039]},{"bxnip":[860],"bxt":[58039],"bxos":[58039],"bxcp":[58061]},{"bxptn":[733],"bxeiropev":[58039],"bxaacjiypets":[58039],"bxijs":[58061]},{"bxrjaav":[58039],"bxiyas":[58039],"bxas":[58039],"bxiydpei":[58039],"bxereopevarv":[58039],"bxan":[58061],"bxws":[58061]},{"bxetrenv":[58039],"bxpv":[58039],"bxeiroptva":[58061],"bxtiroptva":[58061],"bxj":[58201],"bxllewicz":[58315]},{"bxtesh":[1701],"bxirp":[58039],"bx3":[58039]},{"bxerreis":[58039],"bxfziv":[58039],"bxfzcovta":[58039],"bxfzcdvtov":[58039],"bxt":[58061],"bxegpov":[58061],"bxx":[58086],"bxodus":[58183]},{"bxtle":[795],"bxiyrjv":[58039],"bxokavra":[58039],"bxl":[58039],"bxeos":[58039]},{"bxinch":[1122],"bxokavtdpara":[58039],"bxy":[58039],"bxokxrjplav":[58039],"bxokxtjpoi":[58061]},{"bxpa":[1742],"bxlya":[58039]},{"bxij":[58039],"bxvvoovs":[58061],"bxuunct":[58100]},{"bxanel":[1131],"bxlyos":[58039]},{"bxreed":[2300],"bxaos":[58039],"bxj":[58039],"bxf0pos":[58039],"bxerlrvv":[58039],"bxiyarpei":[58039]},{"bxav":[749],"bxott":[1031],"bxrjdrjap":[58039]},{"bxbu":[982],"bxhobk":[2296],"bxe":[58158]}]