[{},{"cbc":[1333,18152],"cba":[1376],"cbeation":[1380,59314],"cbme":[2271],"cbs":[16173],"cbrist":[59237],"cbe":[59436]},{"cbe":[1524],"cbm":[2772],"cbr":[5595],"cbs":[39840],"cbc":[60074]},{"cbr":[1140],"cburch":[2161],"cbw":[9127]},{"cbe":[1607],"cbs":[3044,17913],"cbuld":[59458],"cbr":[60141]},{"cbs":[39946],"cboe":[59390,59400,59401],"cbc":[59507]},{"cbr":[1667],"cbm":[2310],"cbs":[38232]},{"cbrist":[2121,2173],"cbw":[28477]},{"cbeation":[742],"cbm":[906,922],"cbs":[2515],"cbrist":[59044]},{"cbrist":[2198],"cbw":[9296],"cbs":[31500,57334]},{"cbs":[1862,3043]},{"cbm":[1159,59308],"cbs":[2008,27430],"cbrist":[2052],"cburch":[2125],"cbc":[6406],"cbuld":[6607],"cbr":[59532],"cbe":[59977]},{"cbs":[1506],"cbrist":[2312,2786]},{"cbs":[2766,19550,21900],"cba":[30888]},{"cbs":[1500],"cburch":[1702],"cbrist":[2177]},{"cbrist":[2158],"cbuld":[2270],"cburch":[2786,59526],"cbm":[59327]},{"cbeation":[725,746],"cbc":[1149,59350],"cbe":[59327],"cboe":[59395]},{"cbme":[2027],"cbs":[2513,32383,39969],"cbc":[41395]},{"cbw":[28549],"cbme":[60118]},{"cbs":[1856],"cbr":[5508]},{"cbme":[2770],"cbw":[10299],"cboe":[59414]},{"cbm":[2311],"cbr":[5598],"cbs":[6861,7096],"cbe":[59196]},{"cbuld":[2057],"cbe":[59175]},{"cbr":[5507],"cbs":[21480],"cbrist":[60248]},{"cbc":[1399,2575]},{"cba":[1760],"cbm":[53652]},{"cbs":[6059,27183],"cbc":[20247],"cbl":[58395]},{"cbm":[1404,59111],"cba":[1529],"cbl":[58388,58393]},{"cbm":[1632],"cbrist":[1750],"cbs":[2523,59359],"cbl":[58462],"cbr":[59111],"cbc":[59111]},{"cbeation":[724],"cbl":[1824]}]