[{},{"cpr":[23682],"cpub":[60054,60105,60107,60170]},{"cpioted":[1566],"cps":[1869],"cpr":[21243,34044],"cph":[59392]},{"cphe":[805],"cps":[2108],"cpr":[32475]},{"cpr":[19636]},{"cpioted":[59179]},{"cpiite":[1452],"cpr":[43269]},{"cps":[1567],"cpr":[1805,22085]},{"cphe":[1058],"cpiite":[1459],"cpr":[22915,44085]},{"cpiestion":[1204],"cphe":[1412],"cpiite":[1535]},{"cpioted":[1451],"cpr":[32473]},{"cpioted":[873],"cpr":[59378]},{"cphe":[1339],"cps":[1559,19486],"cpr":[19478,22788]},{"cpr":[59399]},{"cphe":[1308],"cpr":[28086,41050]},{"cpr":[62192]},{},{"cpiestion":[6591],"cpr":[22797,24751],"cpioted":[59180]},{"cps":[4267],"cph":[45510]},{"cph":[3316]},{"cpuld":[2524,3945],"cpr":[59344,59403]},{"cpuld":[1813],"cpr":[57122]},{"cpr":[16473,33797,38511],"cph":[45515]},{"cpiestion":[1403],"cpr":[27147]},{},{"cpiite":[1615],"cps":[1942]},{"cpuld":[1167],"cpiite":[1451]},{"cpiestion":[59166]},{},{}]