[{},{"dveaata":[830],"dvina":[841],"dvilized":[867],"dvti":[1587],"dvtrtei":[3621],"dvorak":[21457],"dvd":[40872,45366],"dvrr":[58080]},{"dvtsuco":[1130],"dvocates":[1184],"dvrikuv":[1191],"dvocate":[2116],"dvtsi":[2301],"dvllniy":[3621],"dvtsifcle":[6603,6840],"dvds":[40606]},{"dvertisements":[1555],"dvke":[2159],"dver":[2266],"dvl":[2301],"dvi":[4606,4960]},{"dvija":[1334],"dvd":[43375],"dvlj":[58183],"dverti":[58395]},{"dvifization":[1136],"dvocates":[1445],"dvd":[42075],"dvds":[43923]},{"dvd":[40886,42072,44286,45650],"dvmonism":[58214],"dv7o":[58314]},{"dvmcues":[1150],"dvaglott":[1278],"dvho":[1633],"dvd":[41503,48520,58356],"dvds":[58355,58371]},{"dvertisements":[787],"dver":[1141],"dvd":[42689,44262],"dvds":[45587,58357,58370],"dvr":[58128],"dvaaqiaxeia":[58324]},{"dvertisements":[1140],"dvwtorevy":[1762],"dvd":[40097,45279,45587,45827]},{"dvathrnte":[844],"dvtrirl":[1132],"dvfl":[3038],"dvd":[42411],"dviduri":[58128],"dvarfopi":[58157],"dvopa":[58337]},{"dven":[1358],"dvut":[1521],"dvořák":[41399],"dvd":[45236,45341],"dvipg":[58079],"dvdyxt":[58157],"dva":[58157]},{"dvorak":[27088],"dvd":[40869,41086]},{"dvrell":[1300],"dvd":[41557,43901,44124],"dvtl":[58183],"dvrl":[58183],"dvarov":[58183]},{"dvvcr":[1079],"dvds":[43972,45058],"dvd":[58355,58371]},{"dvds":[45716,45981],"dvre":[58183]},{"dvellest":[1142],"dvsentery":[1293],"dven":[2759],"dvd":[44682,58357,58370]},{"dvdh":[1198],"dvds":[42205]},{"dvoll":[1134],"dvisors":[3031],"dvocates":[58102],"dvd":[59831]},{"dver":[2304],"dvd":[24127,45981],"dvds":[42405,46079,46879,47862]},{"dvity":[762],"dvnariies":[1128],"dvd":[42409,43065,45716,58896],"dvds":[43901],"dvhi":[58128],"dvcambia":[58356]},{"dvr":[1126],"dve":[1131],"dvds":[41256,47510],"dvd":[41296,47605]},{"dvay":[880],"dvrig":[1126],"dvvelleth":[1820],"dvr":[2152],"dvd":[46189]},{"dvlgentiarum":[3936],"dver":[3945],"dvd":[41507,41542,41546,43017,58379,58549,58970],"dvds":[44124,45365],"dvknas":[58262]},{"dvorak":[39208],"dvd":[44142,46649,47718]},{"dve":[2116],"dvd":[41373,44061],"dvds":[45238,45279]},{"dveiiaot":[2115],"dvds":[38567,43700,44658,46770],"dvd":[40864,40977,42018,45340,58844]},{"dvtgifaoov":[1946],"dvfrqcujw":[1946],"dvil":[2112],"dvrnruenterl":[2115],"dvll":[2295],"dve":[2301],"dverthrow":[3945],"dvra":[6345,6596],"dvd":[40763,44222,58366],"dvds":[46869]},{"dvasininkai":[1654],"dvopxav":[1909],"dveder":[2767],"dvd":[40891,43237,43336,47862,49112,49218],"dvds":[44657,46041]},{"dvs":[889],"dvd":[1130,46144],"dvath":[1140],"dve":[2119],"dvij":[2263],"dvetiltt":[5216],"dvorna":[40578],"dvilitfitiom":[58290],"dvoctiuir":[58310],"dvripepci":[58310]}]