[{},{"fkiuw":[844],"fktos":[57991],"fkpvy":[57991],"fkk":[57991]},{"fkflvov":[57991],"fkpi":[57991]},{"fkiii":[1632],"fketvov":[57991]},{},{"fkwv":[57991]},{"fkjjraot":[3618],"fkft":[57991],"fkacrros":[57991]},{"fkrishna":[1151],"fkat":[1752],"fka":[1752],"fkpdr":[57991]},{"fktohmann":[846],"fknown":[1001],"fkjfermen":[1518],"fktlvos":[57991],"fktor":[57991],"fkarbv":[57991],"fkfl":[57991]},{"fktlval":[57991],"fktlvov":[57991],"fkflvos":[57991],"fkflvrj":[57991],"fkflvbs":[57991],"fkfivrjs":[57991],"fktvof":[57991],"fkttopfvdptl":[57991],"fkiroptitrat":[57991],"fktroptvi":[57991],"fkttopfvopfvt":[57991],"fkttoptvovrat":[57991],"fktroptvtrai":[57991],"fktroptvopfvov":[57991],"fkpt":[57991],"fkoraatt":[57991],"fkaraais":[57991],"fkttivdv":[57991]},{"fkwg":[1131],"fkbruary":[2099]},{"fkke":[1759]},{"fkls":[1762],"fkeivos":[57991],"fkkxrjaiav":[57991],"fkkxfiaai":[57991],"fktivov":[57991]},{"fkre":[1695],"fkttotiri":[1762],"fksciu":[1762],"fkoipijfll":[57991]},{"fkjt":[1807],"fkaxfafv":[57991],"fkarovrdpxp":[57991],"fkf10fv":[57991],"fkftvp":[57991],"fkf10tv":[57991],"fktfivas":[57991],"fkfwfv":[57991],"fkvicxaurav":[57991]},{"fkade":[57991],"fktivo":[57991],"fkfi":[57991],"fkak":[57991],"fkarovrdpxov":[57991],"fkiirrm":[57991],"fkfxfvatv":[57991],"fkkf":[57991],"fkfivov":[57991],"fktivrjv":[57991]},{"fkfttxoptvorv":[57991],"fkorraaev":[57991],"fkpart":[57991],"fkpvftr":[57991],"fkijpv":[57991]},{"fkochet":[812],"fkoapijaav":[57991],"fktfvtlq":[57991],"fkparr":[57991],"fka0t":[57991],"fkkxrjalai":[57991]},{"fkif":[832],"fkfivw":[57991],"fkkxqalas":[57991]},{"fkangaroo":[2151],"fkttopevtrai":[57991],"fkkxijcrla":[57991],"fkparovvto":[57991],"fktpdr":[57991]},{"fkond":[4268,4597],"fktvryaav":[57991]},{"fke":[1135],"fka":[6035],"fktlvi":[57991],"fkfivos":[57991],"fkj3t":[57991]},{"fkingdom":[1891],"fkcidr":[57991],"fktrxfccrai":[57991]},{"fkfurther":[799],"fkt":[1854],"fkeys":[2299],"fkrvtefan":[4253,4591,4954],"fka":[5234],"fkytoid":[6039,6325,6585,6831],"fkpa":[57991],"fkxl":[57991],"fkajstv":[57991]},{"fke":[1131]},{"fke":[1252],"fka":[1804],"fkaarov":[57991]},{"fk7ropevfa0a":[57991],"fkttopevopevr":[57991],"fkiropfvfrai":[57991],"fkiropeverat":[57991],"fkextvov":[57991],"fkpov":[57991]},{"fknnt":[2165],"fkkoxvpjsrjaas":[57991],"fktreipdipopev":[57991],"fkiifftco":[57991],"fkfivav":[57991],"fkacrrw":[57991],"fk0axxovatv":[57991]},{"fkom":[737],"fknua":[877],"fkther":[927],"fkincjdam":[4254,4592,4955],"fkxtkrovs":[57991],"fkttivas":[57991],"fkiiorco":[57991]},{"fko":[1623],"fka":[2252],"fkwjation":[2295],"fktpmrrj":[57991],"fksatravrjdrjaopai":[57991]}]