[{},{"ldng":[757],"ldsn":[994],"ldok":[1102],"ldeii":[1132],"ldg21gg2":[1180],"lds":[33223],"ldfjvdn":[58039],"ld31l":[58039],"ldl":[58104]},{"ldie":[1125],"ldr":[1523,1618,4608,4962],"ldtsites":[5783],"ldl3":[58039],"ldraiv":[58039],"ldlitu":[58291],"ldc":[59596]},{"ldp":[2163],"lds":[35396],"ldvixiqv":[58039],"ldcs":[58381,58382],"ldc":[58381,58382,59485]},{"ldpr":[34650],"ldld0dhgb3":[58039],"ldc":[59506],"ldcs":[59558]},{"ldsboro":[1127],"ldo":[58287]},{"ld0":[1139],"ldex":[1558],"lded":[2112],"ldop":[2267],"ldl":[34006],"ldrl":[58039],"ldo":[58039],"ldb":[58262],"ldc":[58630]},{"ldn":[882],"ldl":[30207,34605],"ldls":[34605],"lddd":[58039],"ldi":[58039],"ldapev":[58039],"ldpr":[58039],"ldngdom":[58147],"ldcs":[59579]},{"ldng":[2112],"ldjjs":[2116],"lds":[58039],"ldiios":[58039],"ld9":[58039],"ldc":[59059]},{"ldebly":[1151],"ldandro":[1663],"ldpez":[4265],"ld0r":[58039],"ldpa":[58061],"ldr":[58325],"ldcs":[59137]},{"ld3":[58039],"ldi":[58338]},{"lderlan":[2211],"ldp":[58039],"ldngdom":[58196],"ldc":[58385]},{"ldt":[1762],"ldc":[21351,58379,58390,58391],"ldare":[58039],"ldoxi":[58039],"ldkeaxiii":[58061],"ldivi":[58130],"ldq":[58263],"ldl":[58943]},{"lden":[1025],"ldip":[3622],"ldet":[4603],"ldx":[58039],"ld3u":[58039],"ld13":[58039],"ld0p":[58039],"ldj":[58039],"ldd3dklidadiii":[58039],"ldecpos":[58039],"ldnd":[58196],"ldc":[58412,58599,58768]},{"ldmrr":[58039],"ldc":[58315,59778]},{"lder":[1127],"ldov":[58039],"ldd3d":[58039],"ldc":[59764,59841]},{"ldisetae":[926],"ldnwn":[2113],"ldc":[49286,58375,58526,58666],"ldhm":[58257],"lddlo":[58263]},{"ldgh":[2117],"ldl":[28995],"ldm":[58257],"ldc":[59439]},{"ld5am":[1540],"ldl":[30127],"ldued":[58061],"ldmi":[58124],"ldonci":[58287],"ldc":[58356,58372,58403,58404,58407,58408,58409,58410,58411,58413,58628]},{"ldj4j":[1694],"ldl":[28223],"ldu":[58039],"ldf":[58039],"ld13dvu":[58039],"ldie":[58338],"ldc":[59176]},{"ldng":[2014],"ldmiimdflav":[58039],"ldt":[58039]},{"ldm":[1712],"ldpez":[4263],"ldc":[58380,59488,59504]},{"lder":[1189,1714],"ldc":[59036]},{"lda88ald":[2163],"ldjd44":[2163],"lda":[58039],"ldn":[58039]},{"ldvr":[1136],"lds":[33216],"ldljglgpgr":[58338],"ldgidili":[58338],"ldgtifigp":[58338],"ldft":[58338],"ldc":[58394,58397,58398,58920]},{"ldeifcr":[1144],"lday":[1700],"ldgs":[32846],"ldl":[40816],"ldeinoi":[58039],"ldfr":[58325],"ldt65t6u6":[58325],"ldc":[58799,59405,59604]},{"ldna":[58039]},{"ldease":[2112],"ldlied":[2112],"ldaquat":[2524],"ldl":[36068],"lded":[58032],"ldc":[59293]},{"ldmonton":[1258],"ldsu":[1429],"ldj":[2112],"ldng":[2118],"ldb":[4245],"ld3jl":[58039],"ldol":[58269],"ldngregutianj":[58307],"ldeas":[58329]},{"ldn":[1441],"lds":[3929],"ldgeway":[7094],"ldl":[31670],"ldit":[58039],"ldrcss":[58196]}]