[{},{"mho":[786],"mhiuhed":[6041,6327,6587,6833,7077,7315]},{"mho":[59160],"mhm":[61238,62081]},{"mhlongo":[3017,3307,4245,4584,4948,5763]},{"mhlongo":[3602,3921,5214],"mhe":[5773],"mhm":[61509]},{"mhlongo":[5481]},{"mhe":[1239],"mhlongo":[6034],"mhm":[62330]},{"mhe":[1032],"mhm":[59598]},{"mho":[1131],"mhe":[1137,2162],"mhm":[61075]},{"mhe":[1544]},{"mhe":[885,59146],"mhi":[1131],"mhlongo":[17795,61240]},{"mhe":[1332],"mhi":[3603],"mhm":[62307]},{"mhe":[993]},{"mho":[966,1151],"mhm":[61174]},{"mhi":[1807]},{},{"mhe":[784],"mho":[1760]},{"mhe":[1656]},{},{"mho":[824],"mhe":[59328]},{"mhlongo":[61241]},{},{"mhe":[59341],"mhm":[61171]},{"mhe":[1457]},{"mho":[1140]},{"mho":[738]},{"mho":[905],"mhe":[1194]},{"mhe":[2152]},{"mhe":[982],"mho":[1533]},{"mho":[801,826],"mhi":[2063,3325,59129]}]