[{},{"nxc":[825],"nxxrt":[2295],"nxeiova":[57991],"nxi":[57991],"nxx":[57991],"nxrjpovo":[57991],"nx7no":[57991],"nxovaiois":[57991],"nxtovtkttjs":[57991],"nxt":[57991],"nxijptoaev":[57991],"nxoiov":[57991]},{"nxed":[2115],"nxio":[57991],"nxon":[57991],"nxprn":[57991],"nxn":[57991],"nxtiovts":[57991],"nxoiai":[57991],"nxr":[57991],"nxrjprjs":[57991],"nxtiovs":[57991],"nxovaios":[57991],"nxeidvatv":[57991]},{"nxoirp":[57991],"nxrjbos":[57991],"nxrjyas":[57991],"nxrjyav":[57991],"nxxa":[57991],"nxdipev":[57991]},{"nxox":[1663],"nxis":[2112],"nxea":[2197],"nxeived":[2513],"nxxj":[57991],"nxeovrav":[57991],"nxrjyat":[57991],"nxavp":[57991],"nxovaioi":[57991],"nxeiov":[57991]},{"nxin":[57991],"nxavrjay":[57991],"nxavrjarj":[57991],"nxavrjdrjre":[57991],"nxrjpovoprjaova":[57991],"nxolov":[57991],"nx2":[57991],"nxrjparpa":[57991],"nxetarai":[57991],"nxp":[57991],"nxp0os":[57991],"nxrjpovopoi":[57991],"nxelov":[57991],"nxavaadt":[57991],"nxrjpaidaiaiv":[57991],"nxrjpaidtf":[57991]},{"nxno":[57991],"nxudvaiv":[57991],"nxavda0e":[57991],"nxf":[57991],"nxeov":[57991],"nxyparfy":[57991]},{"nxovrov":[57991],"nxovros":[57991],"nxovtos":[57991],"nxotov":[57991],"nxelarat":[57991],"nxavaa0e":[57991],"nxppps":[57991],"nxppcdap":[57991],"nxavaaffai":[57991],"nxola":[57991],"nxoidpia":[57991],"nxetov":[57991],"nxoiar":[57991],"nxo":[57991]},{"nxavijar":[57991],"nxavrjaai":[57991],"nxoidpiov":[57991],"nxv":[57991],"nxovv":[57991]},{"nxz":[57991],"nxavrjdij":[57991],"nxolwv":[57991],"nxiisy":[57991],"nxeioves":[57991],"nxcivcs":[57991],"nxavaffflai":[57991]},{"nxrfatov":[57991],"nxovrelv":[57991],"nxeove":[57991],"nxaarols":[57991],"nxovtrfiravres":[57991],"nxovrovvras":[57991],"nxwx":[57991],"nx3grog":[57991],"nxavr":[57991],"nxqpovopia":[57991],"nxqpovdpoi":[57991],"nxarcias":[57991]},{"nxamp":[1140],"nxest":[1393],"nxeovd":[57991],"nxetovs":[57991],"nxrjpcopa":[57991],"nxdapa":[57991],"nxeioiri":[57991],"nxcrn":[57991]},{"nxvj":[57991],"nxj3x":[57991],"nxy":[57991],"nxxci":[57991],"nxev":[57991],"nxrjv":[57991],"nxeloves":[57991],"nxs":[57991],"nxqya":[57991],"nxrjpaidii":[57991],"nxrjpa":[57991],"nxjb":[57991]},{"nxovatov":[57991],"nxlovras":[57991],"nxyyas":[57991],"nxypaipa":[57991],"nxyyy":[57991],"nxrjpeis":[57991],"nxoico":[57991],"nxtiov":[57991],"nxpv":[57991],"nxzrrisn":[57991]},{"nxrj0os":[57991],"nxrjpovv":[57991],"nxittitou":[57991],"nxppm0d":[57991],"nxppovo":[57991],"nxovrpaps":[57991],"nxijffos":[57991],"nxtis":[57991],"nxtov":[57991],"nxljbos":[57991]},{"nxrjadpaav":[57991],"nxarela":[57991],"nxoia":[57991],"nxp0ovs":[57991],"nxppcoaev":[57991],"nxudud":[57991],"nx3":[57991],"nxoiio":[57991],"nxouo":[57991],"nxfz":[57991]},{"nxnt":[1557],"nxumalo":[31641],"nxe":[57991],"nxrjpdtpara":[57991],"nxairputuv":[57991],"nxacrpara":[57991],"nxeovektai":[57991],"nxppadij":[57991],"nxppa":[57991],"nxrn":[57991],"nxppidparos":[57991]},{"nxit0os":[57991],"nxrtpa":[57991],"nxoiaplia":[57991]},{"nxaretas":[57991],"nxqpovoptav":[57991],"nxeiarov":[57991],"nxaaavn":[57991]},{"nxdvr":[57991],"nxnx":[57991],"nxppotjropelaoar":[57991],"nxrjpos":[57991],"nxiprei":[57991],"nxntun":[57991],"nxyaiov":[57991]},{"nxpp":[57991],"nxpm":[57991],"nxpaas":[57991],"nxavutpevot":[57991],"nxrjdos":[57991],"nxrjy":[57991],"nxabos":[57991],"nxta0f":[57991]},{"nxilo":[1796],"nxovaiov":[57991],"nxcove":[57991],"nxetaros":[57991],"nxotdpiov":[57991],"nxeurros":[57991],"nxetovas":[57991]},{"nxaia":[57991],"nxelovos":[57991],"nxelar":[57991],"nxeovetpas":[57991],"nxrfios":[57991],"nxeovras":[57991],"nxodo":[57991],"nxnp":[57991],"nxpyij":[57991],"nxicov":[57991],"nxovrpaav":[57991]},{"nxrjtras":[57991],"nxrpr0":[57991],"nxrpror":[57991],"nxrjdtias":[57991],"nxavpaovaiv":[57991],"nxavwptvoi":[57991],"nxeiotriv":[57991],"nxtdvraiv":[57991],"nxrjyrj":[57991],"nxypcopa":[57991],"nxrjpaipa":[57991],"nxrjaiov":[57991],"nxovraiv":[57991],"nxdvois":[57991]},{"nxrxcm":[1856],"nxavrjaovatv":[57991],"nxft0os":[57991],"nxavtia0e":[57991],"nxovatoi":[57991],"nxpyds":[57991],"nxovri":[57991],"nxtfpotjoaplq":[57991],"nxavot":[57991],"nxtypacrtv":[57991],"nxtovt":[57991],"nxto":[57991],"nximng":[57991]},{"nxious":[2064],"nxivovaaiv":[57991],"nxovvtwv":[57991],"nxaiovaa":[57991],"nxartlas":[57991],"nxtiova":[57991]},{"nxumalo":[42501],"nxtgavrts":[57991],"nxvvovres":[57991],"nxas":[57991],"nxijaffrjaav":[57991],"nxeiovs":[57991],"nxifpoc":[57991],"nxxrjxov":[57991],"nxlpara":[57991],"nxrjffos":[57991],"nxty":[57991],"nxtidv":[57991]},{"nxavrjdr":[57991],"nxnj":[57991],"nxjn":[57991]},{"nxaiod":[1454],"nxtova":[57991],"nxeovekteiv":[57991],"nxrjyats":[57991],"nxebvairev":[57991],"nxqp":[57991],"nxqpa":[57991],"nxp0pap":[57991],"nxelova":[57991],"nxidaojt":[57991],"nxijyats":[57991],"nxaktfwv":[57991],"nxarvvovoriv":[57991],"nxoiros":[57991],"nxrj0vv0etrj":[57991]},{"nxp":[2161],"nx87g2o":[2168],"nx37g20":[2168],"nxwnber":[7075],"nxrjatov":[57991],"nxxd":[57991],"nxaico":[57991],"nxrjalov":[57991],"nxalovaav":[57991],"nxialas":[57991],"nxdiov":[57991],"nxolw":[57991]}]