[{},{"pxprem":[1814],"pxage":[4968],"pxo":[57776],"pxtadai":[57776],"pxp":[57776],"pxpev":[57776],"pxlxjstal":[57776],"pxpaxcbreverev":[57776],"pxpaxebreverev":[57776],"pxopevtii":[57776],"pxbev":[57781],"pxov":[57781],"pxiov":[57781]},{"pxphea":[6850,7085],"pxtrrttt":[57776],"pxjsavro":[57776],"pxi":[57776],"pxomai":[57776],"pxols":[57776],"pxaatpqpiai":[57781],"pxcm":[57967]},{"pxponnier":[996],"px3ricrav":[57776],"px0t":[57776],"pxerai":[57776],"pxer":[57776],"pxop":[57776],"px0ev":[57776],"pxlrea0e":[57776],"pxf":[57776],"pxvtos":[57776],"pxvapoi":[57776],"pxr":[57776],"px0cv":[57776],"pxovtat":[57776],"pxdey":[57781]},{"pxhz":[57776],"pxe":[57776],"pxt":[57776],"pxev":[57776],"pxikiav":[57776],"pxnn":[57776],"pxn":[57776],"pxopevr":[57776],"pxrrxjp":[57781],"pxoey":[57781],"pxbs":[57781]},{"pxoev":[57776,57781],"pxa":[57776],"pxttropev":[57776],"pxttrtiv":[57776],"px0ov":[57776,57781],"pxovaev":[57776],"px0r":[57776],"pxeppevos":[57776],"pxacravp":[57781],"pxepae":[57781],"px0ey":[57781],"px8ov":[57781],"pxoep":[57781],"pxovrrt":[57781]},{"pxois":[57776],"pxero":[57776],"pxaatfiripytai":[57776],"pxoma":[57776],"pxtro":[57776],"pxovto":[57776],"pxtto":[57776],"pxtt0":[57776],"pxat":[57781],"px6ta":[57781],"pxao":[57781],"px0":[57781]},{"pxls":[5232],"pxdraeo":[57776],"pxhi":[57776],"px6ov":[57781]},{"pxbpevoi":[57776],"pxovto":[57781]},{"pxmphandl":[1127],"px0tv":[57776],"pxico":[57776],"px3ev":[57776],"pxtitjrov":[57776],"pxdpevot":[57776],"px0ep":[57776],"pxiri":[57776],"pxiriki":[57776],"pxoop":[57781],"px0ev":[57781],"px0e":[57781],"pxovs":[57781]},{"pxpwsstotl":[2115],"pxirikapep":[57776],"pxirlaapep":[57776],"pxfrai":[57776],"pxiriaapev":[57776],"pxirikep":[57776],"pxirikepai":[57776],"pxoo":[57776],"pxdev":[57776],"pxxp":[57776],"pxbpevov":[57776],"pxeioi":[57776],"pxovaav":[57776],"pxirikapev":[57776],"pxopevco":[57776],"pxppeva":[57776],"pxge":[57781],"pxyie":[57863],"pxvvi":[57863],"pxosti":[57991]},{"px0av":[57776],"pxftal":[57776],"px0ts":[57776],"pxdpevov":[57776],"pxdpevos":[57776],"pxope":[57776],"pxtfoy":[57776],"pxgev":[57776],"pxea0e":[57776],"pxftrot":[57776],"pxfiov":[57776],"pxfftv":[57776],"pxotv":[57776],"pxopeva":[57776],"pxopevu":[57776],"pxopevrjs":[57776],"pxppos":[57781],"pxiktav":[57781],"pxettye":[57781],"pxgov":[57781],"pxde":[57781]},{"pxcpb":[1150],"pxoym":[57776],"pxoplvu":[57776],"pxd":[57776],"pxika":[57776],"pxiki":[57776],"pxqev":[57776],"pxikois":[57776],"pxe7t":[57776],"pxgcv":[57781],"pxetal":[57781],"pxdev":[57781],"pxav":[57781],"pxoov":[57781]},{"pxgov":[57776],"pxges":[57776],"pxaertfrrjpritai":[57776],"pxir":[57776],"pxrprato":[57776],"pxqtv":[57776],"pxtkov":[57776],"pxikpv":[57776],"px7":[57781],"pxovra":[57781]},{"pxopevrjv":[57776],"pxopevov":[57776],"pxovre":[57776],"pxtp0pv":[57776],"pxv":[57776],"pxiov":[57776],"pxdtv":[57776],"px6ei":[57776],"pxxrjvarv":[57776],"pxia":[57776],"pxdov":[57781],"pxoe":[57781],"pxqov":[57781]},{"px0apev":[57776],"pxox":[57776],"pxb":[57776],"pxppets":[57781],"pxdopev":[57781],"pxia":[57781],"pxu0as":[57781],"pxas":[57781],"pxikos":[57781],"pxtov":[57781]},{"pxvj":[1132],"pxotected":[3615],"pxderrov":[57776],"pxecrbe":[57776],"pxofdz":[57776],"pxirai":[57781]},{"pxitat":[57776]},{"pxnde":[2115],"pxopevol":[57776],"px6v":[57776],"pxios":[57776],"pxxxti":[57776],"pxpare":[57776],"px0":[57776],"pxov":[57776],"pxifiopevois":[57776],"pxeirete":[57776],"pxrrikevai":[57776],"pxiirikapcv":[57781],"pxstos":[57781]},{"pxi":[786],"pxtro":[1760],"pxptv":[57776],"pxon":[57776]},{"pxomt":[1087],"pxiests":[2120],"pxtov":[57776],"pxdov":[57776],"pxxa":[57776],"pxjsov":[57776],"pxikias":[57781]},{"pxos":[57776],"pxdcv":[57776],"pxovapai":[57776],"pxoptvpv":[57776],"pxvtal":[57781],"pxirikapev":[57781],"pxiriktv":[57781],"pxvapoi":[57781],"pxotf":[57781],"pxirikevai":[57781],"pxottiti":[57781]},{"pxpf":[57776],"px0opev":[57776],"pxtos":[57776],"pxdl":[57781],"pxe":[57889]},{"pxera":[57776],"pxerjpevos":[57776],"pxl":[57776],"pxdav":[57776]},{"px3":[57776],"pxopevoi":[57776],"pxito":[57776],"pxj":[57776]},{"pxophet":[1130],"pxinted":[2112],"pxii":[57776],"pxeittti":[57776],"pxenovaiv":[57776],"pxfi":[57776],"pxoopev":[57776],"pxaarrjaaaa":[57776],"pxovro":[57776],"pxaiaa":[57776],"pxnitpv":[57776],"pxo":[57781],"pxtos":[57781],"pxaaqiipiap":[57781],"pxprpssion":[58017]},{"pxiutlng":[2113],"pxog":[57781],"px0c":[57781],"pxtrovpavrip":[57781],"pxetrwy":[57781],"pxtl":[57781]},{"pxeta":[57776],"pxattaptvov":[57776],"pxdptvov":[57776],"pxoyltpvaa":[57776],"px6s":[57776],"pxetai":[57776],"pxbtv":[57776],"pxtix":[57776],"pxhax":[57967]},{"pxehnoge":[2112],"pxq":[57776],"pxoyccopevt":[57776],"pxdv":[57776],"pxdrepos":[57776],"pxpas":[57776],"pxttreip":[57776],"pxttrcov":[57776],"pxj":[57967]},{"pxqff":[1001],"pxirgatory":[1334],"pxdtjypaav":[57776],"pxoov":[57776],"pxopevos":[57776],"pxftrovras":[57776],"pxrjs":[57776],"pxbv":[57776],"pxux":[57776],"pxl":[57778]}]