[{},{"tfttk":[757],"tffvnurii":[783],"tfiaumr":[783],"tfta":[784],"tfte":[786,876,890,1333,1398],"tfie":[786,942,1195,1234,1342,1401,1493,1508,1554,1608,1644],"tfm":[796],"tfth":[828],"tfyrtle":[834],"tfce":[837],"tfcm":[837],"tfiey":[847],"tfrooklyo":[876],"tfthen":[885],"tfrrneea":[898],"tfoon":[906,1157],"tfibifff":[929],"tfoan":[973],"tfcas":[1000],"tft":[1006,4963],"tfcnt":[1068],"tfr":[1068],"tfhallbe":[1112],"tfyem":[1116],"tfcjforning":[1125],"tfo":[1125,1273,1327],"tfeas":[1128],"tffs":[1129],"tffb":[1142],"tfc":[1171,2175],"tfoporttiefs":[1182],"tfiere":[1342],"tftejiforiiing":[1358],"tfeiv":[1383],"tfke":[1435],"tfcttsmct":[1453],"tfi":[1617,2297,57991],"tffe":[1671],"tfinntsh":[1713],"tfrd":[1719],"tffl":[1732],"tfiink":[1843],"tfuth":[1898],"tfj":[2026],"tftie":[2048],"tfeipg":[2063],"tfcoso":[2099],"tfent":[2113],"tffiairr":[2154],"tfleetivt":[2156],"tfs":[2176],"tfaches":[2185],"tfcll":[2209],"tfoctaj1":[2217],"tfl":[2217],"tff":[2218],"tfources":[2245],"tflntlw":[2252],"tfinu":[2254],"tfllc":[2267],"tfla":[2294],"tfipuffl":[2295],"tfutct":[2297],"tfaw":[2299],"tflne":[2299],"tfcctire":[2299],"tfourctf":[2305],"tfcti":[2507],"tfeat":[2509],"tfti":[2510],"tfcb":[2523],"tfcli":[2762],"tfrfc":[2769],"tfch":[2770],"tfcl":[2771],"tfnintrles":[2773],"tfx":[2776],"tfcf":[3023,3315,3609],"tfijk":[3030],"tfecreiary":[3320],"tfeii":[3625],"tfrvek":[3945],"tfpanuii":[4247],"tfllot":[4248,4586],"tfflcm":[4250,4588,4951],"tfetretary":[4251,4589,4952],"tftftyrefary":[4252,4590,4953],"tfe":[4255,4593,4956],"tfflca":[4268,4597],"tfllmi":[4269,4598],"tforwedan":[5229],"tfap":[5496],"tfre":[5498],"tfec":[6039,6325,6585,6831],"tfrpy":[6848],"tffltm":[7084,7322],"tfoxxwv":[57991],"tfiaiverai":[57991],"tfxerjdrp":[57991],"tfoxxovs":[57991],"tfoxxw":[57991],"tfoxxoi":[57991],"tfav":[57991],"tfttroitjktv":[57991],"tfoxv":[57991],"tfpo":[57991],"tfnxakt":[57991],"tfieovaev":[57991]},{"tffe":[773],"tforkign":[825],"tfas":[1032],"tfte":[1144,1795,2147,6038,6324,6584],"tfijy":[1150],"tfxg":[1653],"tflitem":[1706],"tfttr":[1706],"tfvuad":[1706],"tforooiatiout":[1706],"tfie":[1754,2159,2507,4963,7336,7562,57991,58013],"tfce":[2031,4251,4589,4952],"tfe":[2114,3935],"tfnow":[2117],"tforanto6":[2155],"tfl":[2164,2309,6846,7093],"tfecuo":[2169],"tfor":[2185],"tfiji":[2214],"tff":[2214,2517,4247,6045],"tffwiit":[2215],"tflvq":[2217],"tfot":[2218],"tfeuni":[2265],"tfuendiizig":[2294],"tfn":[2296],"tfwwrlo":[2296],"tflcrrf":[2298],"tfck":[2312],"tffrr":[2314],"tfflee":[2504],"tftetjikic":[2506],"tfi":[2513],"tffer":[2513],"tfmtee":[2777],"tfeai":[2777],"tfiwm":[3024,3316],"tfld":[3024,3316],"tftte":[3028],"tfei":[3618,5482,5504,5776],"tfaidto":[3619],"tfao":[3624],"tfiplind":[3936],"tfre":[4255,4593,4956],"tfo":[4265],"tfd":[4269,4598],"tfubscriptton":[4599],"tfanslatlw":[4965],"tfcirty":[5221,5487,5768],"tfswtr":[5228],"tfoa":[5500],"tflirty":[6035],"tfee":[6038,6324,6584],"tfafiriat":[6038,6324,6584],"tffbrrwtoe":[6051],"tfftla":[6344,6595],"tfw":[6598],"tftaw":[6846],"tfayi":[7329],"tfti":[7572],"tfdrcu":[7574],"tfarrfftar":[7576],"tfutlans":[7576],"tfhir":[7578],"tfrti":[7584],"tfjmvrjs":[57991],"tftas":[57991],"tfrcovi":[57991],"tfrcovr":[57991],"tfkovtra":[57991],"tfraivr":[57991],"tficovrjs":[57991],"tficovr":[57991],"tfoxxov":[57991],"tflx":[57991],"tfxtitfrtv":[57991],"tfavrjaai":[57991],"tfarvrjatv":[57991],"tfxovfaat":[57991],"tfxoiw":[57991],"tffxerrov":[57991],"tftroi":[57991],"tfis":[57991],"tfiro":[57991],"tfxavrj":[57991],"tfitpetrffat":[57991],"tfwxdicrcrav":[57991],"tfrepovres":[57991]},{"tfie":[731,1135,2110,2516],"tfre":[742],"tfi":[779],"tfu":[865],"tfmiimi":[866],"tfee":[947],"tfce":[954],"tfor":[1114],"tftb":[1190],"tfien":[1757],"tffto":[1802],"tfeliefs":[1955],"tfuled":[2053],"tfatc":[2222],"tfork":[2522],"tfanslations":[2525],"tfte":[2773],"tfwhat":[3937],"tfzsr":[6321],"tftanabe":[57991],"tfrpovrprei":[57991],"tfoxxot":[57991],"tfzj":[57991],"tfavarov":[57991],"tfgexev":[57991],"tfjtovv":[57991],"tfyayev":[57991],"tfrerai":[57991],"tfia7ttia0p":[57991],"tfrcovp":[57991],"tfla":[57991],"tfris":[57991]},{"tfie":[763,2517],"tflisutl":[867],"tfio":[871],"tfu":[925],"tfnd":[927],"tf7io":[1155],"tfib":[1336],"tfte":[1350],"tfr":[1598],"tfe":[1691],"tfmilk":[1708],"tfoe":[2007],"tfcro":[2169],"tflrv":[2197],"tffitiolfi":[3036],"tfete":[3326],"tfth":[3616],"tfi0":[4967],"tfty":[4968],"tfs":[6598],"tfiat":[57990],"tfp":[57991],"tfpgavro":[57991],"tfpt":[57991],"tfpi":[57991],"tflotf":[57991],"tfo":[57991],"tfoxxakis":[57991],"tfraivopevr":[57991],"tftacrra":[57991],"tftxr":[57991],"tftaxov":[57991],"tftaxtv":[57991],"tftaxav":[57991],"tftxf":[57991],"tftxrj0rj":[57991],"tfiaxtv":[57991],"tflaxov":[57991],"tf3xr":[57991],"tfvpi":[57991],"tftdrrri":[57991],"tfliaaavtlfltv":[57991],"tfl":[57991],"tfdboyi":[57991],"tfx":[57991]},{"tfib":[828],"tfatc":[1278],"tfce":[1280],"tfte":[1487,7084,7322],"tfu":[1663],"tfye":[1699,58013],"tflat":[1707],"tfje":[1762,2301],"tflaud":[1762],"tfie":[1813,2203],"tfied":[2060],"tfiis":[2120],"tfaere":[2257],"tfalian":[2296],"tfars":[2316],"tfiy":[3621],"tfij":[4252,4590,4953],"tfyayov":[57991],"tfxoltov":[57991],"tfixf":[57991],"tftxtttov":[57991],"tfiotjatv":[57991],"tfiwvi":[57991],"tfw":[57991],"tflxnyl":[57991],"tfrciivr":[57991],"tfoxxco":[57991],"tftatvrjaav":[57991],"tf3vrepa":[57991],"tfrijirav":[57991],"tfrovv":[57991],"tfplv":[57991],"tfpcpa":[57991]},{"tfay":[888],"tfone":[995],"tfc":[1130],"tforlcfs":[1131],"tfee":[1148,2161],"tfi":[1330],"tfs":[2208],"tfe":[2244],"tfhen":[2517],"tfon":[2525],"tfie":[3621],"tfiat":[3927],"tfuel":[4265],"tfijalls":[4265],"tfte":[4602],"tftey":[5784],"tfx0opev":[57991],"tfpas":[57991],"tfitia":[57991],"tfiov":[57991],"tfovata":[57991],"tflte":[57991],"tftov":[57991]},{"tfi":[833,1558],"tfs":[843],"tfmt":[896],"tfting":[995],"tfie":[1742,1853,2772],"tfae":[2063],"tfhmatiew":[2162],"tford":[2179],"tfn":[2299],"tfould":[2301],"tfiudes":[5781],"tfhus":[5785],"tfroftridfi":[57991],"tftappopptv":[57991],"tfkva":[57991],"tfiaxev":[57991],"tftxqoqaav":[57991],"tfrixpacv":[57991],"tfa":[57991],"tfj1":[57991],"tfretxtrcbv":[57991],"tfoxxakts":[57991],"tfrot":[57991],"tfapaylba":[57991],"tfyeipev":[57991],"tftovx":[57991],"tfrpras":[57991],"tfprjv":[57991]},{"tfieir":[758],"tfraymond":[809],"tfwe":[1124],"tfu":[1130],"tfhulai":[1143],"tfrom":[1558],"tfwhat":[2017],"tfie":[2108,2297],"tfla":[2112],"tfdmttdmt":[2162],"tffi":[2509],"tfiis":[2766],"tfofpfxiarpevoi":[57991],"tfxflarais":[57991],"tfai":[57991],"tfovx":[57991],"tfiapl3r":[57991],"tfoswv":[57991],"tfrixoi":[57991],"tfita":[57991],"tfrvxakij":[57991],"tflsc":[57991],"tfv":[57991],"tfox":[57991],"tfukt":[57991]},{"tfcese":[727],"tfee":[881],"tffi":[1074],"tfcc":[1130],"tfe":[1187],"tfife":[1590],"tfals":[1693],"tfih":[1703],"tfrodtm":[1762],"tfaj":[1762],"tflm":[2112],"tfie":[2247,2502,2503],"tfora":[2254],"tfmaniii":[2296],"tfeis":[2502],"tfinf":[2507],"tffe":[2508],"tfito":[2508],"tfons":[5224,5490,5771],"tfiavfj":[57991],"tftax":[57991],"tfaoidsx":[57991],"tftrjprj":[57991],"tfiico":[57991],"tfiolxtvaavro":[57991],"tfro":[57991],"tffkcrriffdi":[57991]},{"tfw":[591],"tfa":[591],"tfenrfter":[591],"tfce":[722],"tfaat":[749],"tfi":[794],"tfie":[947,1537,2165,2525,3038],"tff":[1055,1703,57991],"tfee":[1706],"tffwe":[1762],"tflere":[1793],"tful":[2116],"tfind":[2253],"tfiey":[2507],"tfe":[2516],"tfpflwmm":[3032],"tfte":[4600],"tfft":[4606,4960],"tfifngs":[6342,6593],"tftwvrjs":[57991],"tftp":[57991],"tfiftopr":[57991],"tfiaxov":[57991],"tfj":[57991],"tfipti":[57991]},{"tfvr":[591],"tfc":[891,1395,2777],"tfeok":[891],"tfce":[982,2299,3033],"tfe":[1146,2260],"tfot":[1150],"tfwn":[1553],"tfyals":[1556],"tftttor":[1762],"tfnir":[1762],"tffe":[2164],"tfery":[2168],"tforaup":[2205],"tffedoffi":[2264],"tfee":[2507],"tfte":[2520],"tfie":[2775,5233],"tftw":[4258],"tff":[5238,5495],"tfsaxtv":[57991],"tfiidxrjv":[57991],"tfrr":[57991],"tfiiv":[57991],"tfx06vra":[57991],"tfrixakf":[57991],"tfrvxiikfj":[57991],"tfpxovro":[57991],"tfpxero":[57991],"tfpexxev":[57991],"tfiusiu":[57991],"tfveykev":[57991],"tflz":[57991]},{"tfiitm":[1127],"tfi":[1550],"tftlcrilk":[1762],"tft":[1762,57991],"tfcte":[1791],"tfe":[2018,2217,5237,5494],"tfthleelntb":[2158],"tfie":[2258],"tfde":[2521],"tfiew":[3321],"tfiey":[4594,4957],"tfieir":[6039,6325,6585,6831],"tfwxakl":[57991],"tfyaytv":[57991],"tfpoapevovaiv":[57991],"tfrayaxriv":[57991],"tfcds":[57991],"tfosus":[57991],"tfovaiav":[57991],"tfxvlrat":[57991],"tfcraupfs":[57991],"tfpptbnov":[57991],"tfore":[57991],"tfprei":[57991],"tftacrixtvcrav":[57991],"tfcv":[57991],"tf0vr":[57991],"tfrjrtrrt":[57991],"tftaiktv":[57991],"tfoxvs":[57991],"tf8r":[57991],"tfbqki":[57991],"tfpeaev":[57991],"tfft":[57991],"tfioefibs":[57991]},{"tfie":[1037],"tfeill":[1041],"tfas":[1484,3038],"tfe":[1547],"tfjatik":[1693],"tfiilbt":[1700],"tfccli":[1710],"tfrrrriit":[1713],"tfk":[1742],"tfaatinatjon":[1757],"tflfulu":[1791],"tfv":[1791],"tflyword":[2052],"tfns":[2110],"tfebster":[2215],"tfiunssm":[2517],"tfbr":[57991],"tftatrnapr":[57991],"tfs":[57991],"tf0txov":[57991],"tfoteitw":[57991],"tfoxftos":[57991],"tfiv":[57991],"tfdvres":[57991],"tfttcv":[57991],"tfxco":[57991],"tfvx":[57991],"tftdpatv":[57991]},{"tfnless":[715],"tform":[837],"tfny":[986],"tfou":[1125],"tferi":[1340],"tfe":[1700],"tfeefrk":[1710],"tftrul":[1791],"tfauons":[1791],"tfa":[1805],"tfiny":[1805],"tft":[1805,1812],"tfi":[1807],"tfte":[2513],"tfsm":[2771],"tftwhih":[3030],"tfkrgy":[3925],"tfiat":[4949],"tfxemais":[57991],"tfpcmrvvrjv":[57991],"tfxwvai":[57991],"tfjcrov":[57991],"tftxovrts":[57991],"tfov":[57991],"tfrdyaxriv":[57991],"tfiovxoppv":[57991],"tfiwka":[57991],"tfianricrdr":[57991],"tfir":[57991],"tftatvps":[57991],"tfrvxdaap":[57991],"tfyvxakij":[57991],"tfxxw":[57991],"tftcokas":[57991]},{"tft":[740],"tfib":[829],"tfc":[940],"tfa":[950],"tfeeae":[1022],"tfnc":[1130],"tftacongress":[1547],"tfi":[1696],"tfhan":[1807],"tfiut":[1807],"tfluth":[2058],"tftylor":[2112],"tfinidad":[2244],"tficoter":[3943],"tfiis":[4256],"tfiraacate":[4604],"tffftky":[5779],"tfiat":[6848],"tfr":[57991],"tfiraapatv":[57991],"tfrpadpxrjs":[57991],"tfrvxa":[57991],"tfttiv":[57991],"tfrv":[57991],"tftxdanjatv":[57991],"tffvx":[57991],"tfz":[57991],"tfitov":[57991],"tfxtitt":[57991],"tfpeov":[57991],"tfws":[57991],"tfxi":[57991],"tfxtvaf":[57991],"tfpxdpe0a":[57991],"tfxeirovcriv":[57991],"tfxovfjv":[57991]},{"tfhe":[751],"tfnp":[860],"tfjlott":[921],"tfv":[1130],"tflcgraplicr":[1132],"tfiat":[1138],"tfar":[1196],"tfok":[1645],"tful":[2112],"tfs":[2304],"tfiserenf":[2759],"tfainen":[4602],"tfiookav":[57991],"tfidaraaas":[57991],"tfarjalv":[57991],"tfrlvy":[57991]},{"tfik":[742],"tfljnes":[760],"tfce":[776,1866],"tfie":[1088,1808,2048],"tfis":[1177],"tftie":[1233],"tff":[1645],"tfisg":[1760],"tfjr":[1860],"tfyat":[2016],"tfork":[2161],"tfavel":[2163],"tfc":[2316],"tfte":[2507],"tfieir":[4258],"tfiaivrj":[57991],"tfidivpaev":[57991],"tfiw":[57991],"tfidpatv":[57991],"tfpf":[57991],"tfixaacprjpti":[57991],"tfoiw":[57991],"tfdxtv":[57991],"tftaivp":[57991],"tfiajvrp":[57991],"tfiaivr":[57991],"tfvatv":[57991],"tftcovrj":[57991],"tfravijs":[57991],"tfldrjtrtv":[57991],"tfrvxris":[57991],"tftev":[57991],"tfrpaapxovvros":[57991],"tfrayerai":[57991],"tfopelats":[57991]},{"tfialthes":[796],"tfrnits":[798],"tfor":[818],"tfnp":[832],"tfioo":[836],"tfie":[878],"tfons":[899],"tfce":[1046],"tft":[1759],"tfmtdd":[1760],"tfboth":[1799],"tfeit":[2003],"tfant":[2128],"tfain":[2146],"tfthe":[2511],"tfzdpi":[4266,4595],"tfte":[5218,5484,5765],"tfrdflov":[57991],"tfidijatv":[57991],"tfvai":[57991],"tfpfxxtv":[57991],"tfrarriaavtos":[57991],"tfoxiv":[57991],"tftaaixtvaav":[57991],"tfyr":[57991],"tfxoub":[57991],"tfrvaikrjv":[57991],"tffxeve":[57991],"tfrovevaare":[57991],"tfoavrjs":[57991],"tfctxdrjrr":[57991],"tfxiifreat":[57991]},{"tfie":[760,920,6342,6593],"tfi":[809,839],"tfosw":[985],"tfe":[1130],"tffi":[1144],"tflil":[2113],"tfte":[3945,5233],"tfcourpc":[6047],"tfrco":[57991],"tfiaaixtvatv":[57991],"tfianriaavro":[57991],"tfiavepd":[57991],"tfyeipep":[57991],"tfrcoreivi":[57991],"tfrvxijs":[57991],"tftavps":[57991],"tfap":[57991],"tfrvatovpevos":[57991],"tfrixos":[57991],"tfrarvriv":[57991],"tfrarvr":[57991],"tfyrovv":[57991],"tfade":[57991]},{"tfhat":[749],"tfbis":[749],"tftalists":[982],"tfin":[982],"tfood":[997],"tfte":[1132],"tfao":[1457],"tfca":[1701],"tftitil":[1714],"tfle":[1754],"tfie":[1848],"tff":[2049],"tftey":[2757],"tfucks":[5216],"tfitao":[5781],"tflma":[57991],"tfd":[57991],"tfldaraaas":[57991],"tfos":[57991],"tfpoyvaxret":[57991],"tfpoerreraypevovs":[57991],"tfrprac":[57991],"tftaxev":[57991],"tftt":[57991]},{"tfiat":[801,826],"tfanctitwahon":[815],"tfie":[823,2045,2305],"tff":[1003],"tfars":[1590],"tftare":[1701],"tfae":[1704],"tfab":[1704],"tflack":[1892],"tffbride":[2014],"tfcintnakers":[2247],"tfou":[2507],"tfcts":[6600],"tffriv":[57991],"tfixtirtv":[57991],"tftxtnov":[57991],"tfxos":[57991],"tfratvi":[57991],"tfuxaatfirjprjaav":[57991],"tflaxtv":[57991],"tfrwvr":[57991],"tfln":[57991],"tfll":[57991],"tfiwv":[57991],"tf0exov":[57991],"tfpfcaro":[57991]},{"tfaaf":[801,826],"tfbiblt":[992],"tfv":[1032],"tfemfcie":[1149],"tfhing":[1231],"tftft":[2094],"tford":[2107],"tftat":[2147],"tfr":[2152],"tftf":[2211],"tfe":[2288],"tfjhat":[2312],"tfwhy":[2521],"tft":[2770],"tfrulr":[3943],"tfev":[3944],"tfess":[4969],"tfc":[5763],"tfie":[6037,6323],"tfyytkev":[57991],"tfiarrnaqr":[57991],"tffflai":[57991],"tfrcovel":[57991],"tftaivys":[57991],"tfraytiv":[57991],"tfrjpidoprjv":[57991],"tfttxcbv":[57991],"tfxtvrarci":[57991],"tftwktv":[57991],"tftatvrj":[57991]},{"tfieir":[765],"tfe":[837],"tflp":[899],"tfiis":[1092],"tfooug":[1131],"tfa":[1132],"tflfle":[1181],"tfoese":[1849],"tfcphh":[1856],"tfie":[2096],"tfyligious":[2168],"tfrath":[2504],"tfte":[3331],"tft":[4246],"tfl":[4253,4591,4954],"tfleir":[4967],"tfadd":[7090],"tfiloh":[15663],"tfriaxrjv":[57991],"tfkovaav":[57991],"tfpgavto":[57991],"tfpid":[57991],"tfpvopfvoj":[57991],"tfoexov":[57991],"tfjrovv":[57991],"tfrayelv":[57991],"tfedrpovv":[57991],"tfrarvpv":[57991],"tfitoktv":[57991],"tfkttof":[57991],"tfavdrov":[57991],"tfpdtlpaptv":[57991],"tfxt":[57991],"tfxijapovijv":[57991],"tfxotapia":[57991],"tfovres":[57991]},{"tfatch":[781],"tfnaity":[870],"tfoaz":[984],"tferir":[1127],"tfas":[1137],"tfee":[1150],"tfc":[1186,1855],"tft":[1741],"tftlu":[1742],"tfye":[1954,2169],"tfe":[2120],"tfood":[2208],"tfce":[2218,7565],"tfd":[2218],"tforrect":[2264],"tftn":[2503],"tfie":[2756],"tfte":[3621],"tftvxakas":[57991],"tfavara":[57991],"tfipa":[57991],"tfoa":[57991],"tffr":[57991],"tfpfis":[57991],"tflijjl":[57991],"tfitpovrts":[57991],"tfravxa":[57991],"tfhxiv":[57991],"tfrriov":[57991],"tfrepovret":[57991]},{"tfiie":[738],"tfhnt":[777],"tfa":[777],"tfaaf":[798],"tfie":[941,955,2313],"tfre":[1143],"tfren":[1183],"tfw":[1751],"tfar":[1812],"tfcine":[1880],"tfas":[2070],"tfle":[2148],"tfhigh":[2206],"tfte":[2209,3933,7323],"tft":[2215],"tfcripturul":[2293],"tfoe":[2309],"tfi":[2503],"tfhale":[2763],"tf3":[3610],"tf2":[3922],"tfkl":[5785],"tftt0r":[57991],"tfiav":[57991],"tfias":[57991],"tfvaovaiv":[57991],"tfitiv":[57991],"tfvaavtts":[57991],"tfpeis":[57991],"tfpavq":[57991],"tfls":[57991],"tftoixtv":[57991],"tflcflxpto":[57991],"tfjxoyds":[57991],"tftsdprjv":[57991],"tf3axtv":[57991],"tfyjpdvorj":[57991],"tfrvovaa":[57991],"tfctixaprjv":[57991],"tfjavrjv":[57991],"tflaxav":[57991],"tfocrw":[57991],"tfrrprov":[57991],"tfravpatrai":[57991],"tfpairi":[57991],"tfdxaaaav":[57991]},{"tfhose":[749],"tfiat":[759,2757],"tfafff":[797],"tfaat":[800],"tful":[808],"tfjtat":[828],"tfat":[830],"tfe":[839],"tfter":[897],"tfevrewre":[1143],"tfatch":[1313],"tfef":[1380],"tfie":[1621,1710,1999,2116],"tfpe":[1697],"tfc":[1751,2168],"tffe":[1752],"tfte":[2006,2201],"tfons":[2115],"tfoops":[2168],"tfr":[2203],"tftft":[2299],"tfri":[3028],"tfesirabfe":[3319],"tfs":[3325],"tfiev":[4585],"tfrovov":[57991],"tfaoiov":[57991],"tftdnriaa":[57991],"tfti":[57991],"tfrixar":[57991],"tfrvaiv":[57991],"tftoo":[57991],"tfsvxijs":[57991],"tfsixa8t":[57991],"tfsoi":[57991],"tfsavipasais":[57991],"tfvtria":[57991],"tfvoigev":[57991],"tfiarnvov":[57991],"tfiartivov":[57991],"tfrjprjydpti":[57991],"tfaiktv":[57991],"tfapearrjaev":[57991],"tfdpaei":[57991],"tfiovxtvatv":[57991],"tftavtpd":[57991]},{"tfohn":[733],"tfould":[799],"tfaai":[832],"tffte":[838],"tflia":[838],"tffle":[1528],"tffc":[1532],"tflevivk":[1617],"tfia":[1689],"tfr":[1946],"tfi":[1946],"tfy":[1946],"tffl":[1946],"tfiia":[1946],"tfext":[1968],"tfiat":[2158,4966],"tfernatlonalizatlon":[2208],"tfrj":[2265],"tfut":[2295],"tfatltag":[2299],"tfte":[3928],"tfpdvovs":[57991],"tfvoigtv":[57991],"tfkvov":[57991],"tfpovaaxijp":[57991],"tfrjrtitt":[57991],"tfidakavtv":[57991],"tfnlyjj":[57991],"tfiiovi":[57991],"tfpoarjv":[57991],"tfrdidov":[57991],"tfri":[57991],"tfieatmra":[57991],"tfjprjaovaiv":[57991]},{"tfie":[758,837,838,1284,1407],"tftfuw":[777],"tfrmsteaf":[777],"tfds":[779],"tfnd":[796],"tfos":[799],"tfas":[799,1141],"tfaen":[829],"tfllld":[836],"tfrt":[849],"tfc":[876],"tfn":[1019],"tftwpico":[1069],"tforth":[1168],"tfronp":[1588],"tfatchtou":[1622],"tfain":[1742],"tfinity":[1750],"tfjj":[1909],"tfu":[2117],"tfking":[2143],"tfar":[2504],"tfle":[3930],"tforlti":[4266,4595],"tfian":[4966],"tffls":[6045],"tfelegraph":[6047],"tfate":[6605,6842],"tfoj":[57991],"tfnep":[57991],"tftanrttrdr":[57991],"tffai":[57991],"tfpiflav":[57991],"tfaveirai":[57991],"tfavipaxrd":[57991],"tfaavtp":[57991],"tfaavtpa":[57991],"tfrevyeroraav":[57991],"tfpr":[57991],"tfaptriv":[57991],"tfirjaiv":[57991],"tfp0a":[57991],"tfrtaxas":[57991],"tfrix":[57991],"tfrixdpyvpoi":[57991],"tfaxovvtwv":[57991],"tfaxels":[57991],"tfaixel":[57991],"tfrixd":[57991],"tfrixovvras":[57991],"tfnxcdv":[57991],"tfaxodeoi":[57991],"tfrixijpan":[57991],"tftixla":[57991],"tfjpovovvtes":[57991],"tfrpovelre":[57991],"tfipovipoi":[57991],"tfivxtikrjs":[57991],"tfivxaktis":[57991],"tfptjv":[57991],"tfivxrjs":[57991],"tfivatovrai":[57991],"tfitaet":[57991],"tfietaaro":[57991],"tfiatva":[57991],"tfiaivp":[57991],"tfxjjvrjs":[57991],"tfxavrjv":[57991],"tfkotia":[57991],"tfyvxals":[57991],"tflovxt":[57991]},{"tfflnking":[32],"tfiri":[76],"tfttf":[76],"tfhe":[746],"tfry":[776],"tfc":[798,979],"tfn":[799],"tfimgs":[827],"tfrraeo":[827],"tfieta":[829],"tfiem":[829],"tfnenfal":[829],"tfaaf":[837,845],"tfir":[837],"tfiefinishedmyshrgt":[838],"tfr":[839,2204],"tfiink":[881],"tfyr":[885],"tft1":[890],"tfs":[894],"tfie":[930,3319,4602],"tfeg":[939],"tfirf":[1001],"tfsh":[1039],"tft":[1076],"tfty":[1124],"tfto":[1131],"tfic":[1132],"tfas":[1143],"tfgcly":[1330],"tfle":[1333],"tfirntutiih":[1602],"tfgod1":[1608],"tfu":[1609],"tfatch":[1692],"tfvte":[1696],"tfairi":[2154],"tfginppect":[2163],"tfce":[2163,4264],"tfpd":[2164],"tfee":[2166],"tfsane":[2196],"tfcct":[2197],"tfaite":[2216],"tfotoatoww":[2251],"tfuc":[2252],"tfinpdom":[2256],"tfwhat":[2258],"tfaa":[2260],"tfe":[2306],"tfadio":[2307],"tfetu":[2310],"tftis":[2504],"tfo":[2524],"tfte":[2756,2772,3617,4255,4593,4594,4956,4957,5224,5490,5771,6044,6055,6330,6332,6590,6836,6839,7080,7083,7314,7318,7321],"tfcouffa":[3017],"tfrorid":[3025],"tfdsvuflfane":[3030],"tfa":[3617,3619,3932],"tfiitirn":[3619],"tftfeexai":[3624],"tfien":[3933],"tfiingr":[3934],"tfcis":[4594,4957],"tftts":[4963],"tfje":[5224,5490,5771],"tfy":[5233,7334,57991],"tfcm":[5785],"tfts":[6050],"tfeic":[6055,6332],"tffen":[6339],"tfta":[6598],"tfauc":[6844],"tfat":[7097,7326],"tfaw":[7584],"tfiva":[57991],"tfanapbv":[57991],"tfaybpaatv":[57991],"tfotwi":[57991],"tfidaprois":[57991],"tftbopos":[57991],"tfvaiaarr":[57991],"tftai":[57991],"tflmoi":[57991],"tfitpdittvtrtv":[57991],"tfraivtaflt":[57991],"tfdr":[57991],"tfkovcrav":[57991],"tfx0a":[57991],"tfxoitb":[57991],"tfye":[57991],"tfjpopetp":[57991],"tfi":[58013]}]