[{},{"tmtrr":[760],"tmr":[762,2156],"tmih":[764],"tms":[778,1125,2120],"tmwiasr":[782],"tmk":[783],"tmder":[792],"tmction":[808],"tmn":[812],"tm4":[833],"tmgedy":[833],"tmace":[834],"tmuhacj":[841],"tmica":[846],"tmsrttttr":[848],"tmlix":[894],"tmno":[911],"tmeectiom":[926],"tmw":[1143],"tmnps":[1208],"tmft":[1319],"tmiicipal":[1443],"tmb":[1453],"tmltunm":[2160],"tmiltsned":[2215],"tmriu":[2218],"tmly":[2253],"tmof":[2297],"tmeensored":[2299],"tmhttam":[2302],"tmfeiteired":[2509],"tmpllanca":[2761],"tmonw":[2773],"tme":[3019,3311,3605],"tmcenaored":[3031],"tmthly":[4263],"tmi":[5229],"tmuri":[7333],"tmle":[7583],"tmj":[30222],"tmaroxrjv":[57991],"tmanv":[57991],"tmro0a":[57991],"tmrdaati":[57991]},{"tmsly":[1150],"tmed":[1443],"tmly":[1881],"tmwe":[2114],"tmmgffs":[2146],"tmrto":[2157],"tmtirg":[2164],"tmiv":[2246],"tmfor":[2257],"tmhj":[2297],"tmno":[2297],"tmatn":[2304],"tmntnn":[2305],"tmato":[2308],"tmtt":[2503],"tmtast":[2514],"tmacf":[3024,3316],"tmmtriea":[3027],"tmrat":[3613],"tmfiri":[3618],"tmimin":[4968],"tmiulaucn":[5224,5490,5771],"tmmto":[5231],"tmrty":[5504,5776],"tmr":[5504,5776],"tmntdaucn":[5504,5776],"tmft":[5764],"tmvatlnn":[6046],"tmi":[6051],"tmtlatlw":[6597],"tmwtnge":[7090],"tmdij":[57991],"tmaro":[57991],"tmee":[58013]},{"tmt":[809,1133],"tmw":[821],"tmat":[843],"tmth":[868],"tmn":[873],"tment":[1128],"tmy":[1132],"tmnd":[1475],"tmmuy":[1632],"tmthr":[1637],"tmd":[2118],"tmhy":[4594,4957],"tmtikis":[57991],"tmpe0a":[57991],"tmhtoi":[57991],"tm0vpias":[57991]},{"tmt":[810],"tmm":[822],"tmie":[882],"tmrp":[1140],"tmrnri":[1149],"tmd":[2112,2507],"tmtas":[6846],"tmj":[30144]},{"tmw":[1131],"tmrat":[1137],"tmnic":[1523],"tmust":[1947],"tmim":[50766]},{"tmmner":[183],"tmo":[957],"tmfi":[1130],"tmtm":[1130],"tmg":[1150],"tmnple":[1520],"tmssj":[1807],"tmn":[1823],"tmproved":[2112],"tmd":[2200],"tmnee":[3028],"tmderjtif":[3621],"tmngs":[6583],"tmim":[9101],"tmj":[30310,57991],"tmdi3x":[57991],"tmij":[57991],"tmrlbd33":[57991],"tmil13":[57991],"tmrlb":[57991],"tmypj":[57991],"tmaroxiov":[57991],"tmaroxuiv":[57991],"tmxoprjyovptvov":[57991],"tmefravtias":[57991],"tml":[58014]},{"tmef":[48],"tmiflc":[591],"tmkr":[591],"tmg":[957],"tmmbnse":[1135],"tmjirdtrv":[1752],"tmd":[2115],"tmb":[2159],"tmsura":[2303],"tmologie":[5781],"tmartvaav":[57991],"tmriarevkapev":[57991]},{"tme":[742],"tmevss":[1127],"tml":[2114,32487],"tmj":[2118],"tmes":[2517],"tmypa":[57991],"tmafyaxovs":[57991],"tmflovxris":[57991]},{"tmcer":[1227],"tmr":[1706],"tms":[2205],"tmt":[2247],"tmndns":[57991],"tmcrrrjplfav":[57991]},{"tmg":[820],"tms":[995],"tmh":[1706],"tmlacki":[1809],"tme":[1866],"tmdershmding":[2115],"tmttm":[2516],"tmrxppaptva":[57991],"tmdi3jij":[57991],"tmgy3":[57991],"tmovap":[57991]},{"tmcirte":[591],"tmguisli":[874],"tmiou":[1131],"tmtne":[1637],"tmart":[1762],"tml":[1853],"tmd":[2062],"tmdersland":[2116],"tmemie":[2295],"tma":[3032],"tmj":[30308],"tmno0f7":[57991],"tmnbffqaiv":[57991],"tmnoptvoptvav":[57991],"tmpixl":[57991],"tmaktyj":[57991],"tmakonovvtts":[57991],"tmttkonr":[57991],"tmanonov":[57991],"tmardra":[57991],"tmatoxas":[57991],"tmatoxr":[57991],"tmarpty":[57991],"tmtfravatt":[57991],"tmptivai":[57991],"tmv":[57991],"tmardptvos":[57991],"tmvov":[57991],"tmarpttfaiv":[57991],"tmrxpptiokevai":[57991]},{"tmdcrstnnd":[2117],"tmne":[2129],"tmdof":[2255],"tmyvdiati":[57991],"tmno0lav":[57991],"tmdvpiav":[57991],"tmroidrjaiv":[57991],"tmacfiaxovs":[57991],"tmaroxijv":[57991],"tmovpiais":[57991]},{"tmth":[778],"tmewfo":[1129],"tmy":[1151],"tmgelic":[1527],"tm4":[1693],"tmfa":[1710],"tmt":[1710],"tmr":[1710],"tmtof":[1762],"tml":[1791],"tmne":[2113],"tmatt":[2136],"tmdx3":[57991],"tmdn":[57991],"tmji":[57991],"tmvoxa":[57991],"tmtv":[57991]},{"tmtore":[1334],"tmumlna":[1710],"tmhf":[1791],"tmre":[1791],"tmy":[1791],"tmu":[1791],"tmeut":[1791],"tmrtimr":[1807],"tmtra":[1898],"tmiviors":[2115],"tment":[2115],"tmnedinqng":[3930],"tms":[7097,7326],"tmarpttp":[57991],"tmexdw":[57991],"tml":[58013]},{"tmk":[1095],"tmso":[1095],"tmv":[1151],"tmfflycjjiifismsits":[1179],"tmwriwrnrntrf":[1236],"tmamvcl":[1497],"tmned":[2112],"tms":[2123],"tmg":[2195],"tmyvd":[57991],"tmdi":[57991],"tmxuilu":[57991],"tmqdvx":[57991],"tm3dhdn0":[57991],"tmdh":[57991],"tmd":[57991],"tmrlq":[57991],"tmda":[57991],"tmdll":[57991],"tmdli":[57991],"tmxnv":[57991],"tmxnu":[57991],"tmdyv":[57991],"tmaarptv":[57991],"tmrtipaaptvov":[57991]},{"tmd":[824],"tmg":[877],"tme":[929],"tmtoi":[1140],"tmtm":[1645],"tmmon":[1940],"tmto":[2116],"tmmed":[2119],"tmev":[57991],"tmux":[57991]},{"tmable":[836],"tmtilm":[1126],"tmr":[1130],"tmuh":[1140],"tmei":[1618],"tmftdcum":[1760],"tmflt":[1760],"tmth":[1760],"tmn":[2113],"tmj":[30292],"tmira":[57991],"tmjparav":[57991],"tmatpty":[57991]},{"tmieh":[1132],"tmve":[1136],"tmtan":[1760],"tmyed":[1760],"tmiseries":[1878],"tmim":[58013],"tmeii":[58014]},{"tmm":[815],"tmoses":[1003],"tmrmm":[1607],"tmd":[2772],"tmra":[4605,4959],"tmarpe":[57991]},{"tm3":[752],"tmiiiled":[910],"tmtf":[1087],"tme":[1620],"tmdouhtsdly":[1706],"tmaater":[1706],"tmpoi":[1970],"tmy":[2055],"tmcfocovovv":[57991]},{"tmliou":[961],"tmi":[1127],"tmitating":[1652],"tmtmahmb":[1742],"tmeans":[1744],"tmj":[2014],"tmewnaf":[2112],"tmetmta":[2112],"tmfffefet":[3923],"tmel":[5229],"tmti":[6839,7083,7321],"tmrxrjpoitai":[57991],"tmypatfri":[57991],"tmrxr":[57991]},{"tmgn":[1131],"tmttbge":[1183],"tmqorsged":[1751],"tmt":[1751],"tmjess":[2118],"tmea":[2152],"tms":[5225],"tmrxrjp":[57991],"tmovpias":[57991],"tmoz":[57991],"tmmd":[58013]},{"tmsfotted":[743],"tmperator":[797],"tmch":[950],"tmwt":[1126],"tmto":[1534],"tmie":[1601],"tmftaman":[1741],"tmt":[2305],"tms":[4247],"tmitenputten":[5230],"tmv":[18777],"tm0v":[57991],"tmtrrpacjit":[57991],"tmartvaart":[57991],"tmytia":[57991],"tmartvatv":[57991],"tmartvtrt":[57991],"tmartv":[57991],"tmartvov":[57991],"tmat":[57991]},{"tmv":[867],"tmrsteth":[1131],"tmde":[2120],"tmrt":[2262],"tmver":[4585],"tmov":[57991],"tmaclu":[58014]},{"tmt":[798],"tmth":[1044],"tmve":[1336],"tmi":[1751],"tmer":[1855],"tminution":[2116],"tmlpaipjptvos":[57991],"tmaroxp":[57991],"tmovaiov":[57991]},{"tmr":[712],"tmdesnable":[862],"tmoperak":[1143],"tmz":[2280],"tmhbe":[2315],"tme":[4253,4591,4954],"tmfi":[5218,5484,5765],"tmffxrjpa":[57991],"tmkaxtarjrai":[57991],"tmavvax0p":[57991]},{"tml":[1129],"tmmli":[1137],"tmbli":[2019],"tmt":[2112],"tmhllshed":[2113],"tmd":[2120],"tmes":[2120],"tms":[57991],"tmjpmra":[57991],"tmyparpr":[57991],"tmriatfvpai":[57991],"tmid":[57991],"tma3jj311l":[57991],"tmcf":[57991],"tmgi3iip":[57991],"tmar":[57991],"tmdsdll":[57991],"tmiu":[57991]},{"tmit":[977],"tmgs":[1126],"tmmpeter":[1455],"tmsu":[1619],"tmss":[2112],"tment":[2113],"tmclertaken":[2119],"tme":[2119],"tmbigerbtg":[2295],"tmndltug":[2302],"tm9":[3308],"tma":[20432],"tmaroxa":[57991],"tmart":[57991],"tm0paovaiv":[57991]},{"tmi":[782],"tmags":[829],"tmnl":[834],"tmporfiento":[839],"tmg":[1078],"tmda":[1131],"tma":[1328,4965,5764],"tmns":[1533],"tmniiitiuiilhti":[1588],"tme":[1699,2777],"tmee":[1813],"tmiuilijij":[1850],"tms":[2114,2511],"tmri":[2115],"tmlmrt":[2118],"tmius":[2120],"tmslve":[2165],"tmy":[2294],"tmne":[5234],"tmb":[6041,6327,6587,6833,7077,7315],"tmnsjafion":[6055,6332],"tmcjjavtiav":[57991],"tmyvuratt":[57991],"tmxliil":[57991],"tmaroxwv":[57991]}]