[{},{"uwsts":[1131],"uwi":[1184],"uwal":[1442],"uwl":[2266],"uwi7":[2302],"uwudlsla":[4254,4592,4955],"uwttto":[7580],"uwasi":[32343]},{"uwt":[1663],"uwy":[1799],"uwh":[4601],"uwd":[6344,6595,7579],"uwv":[57778]},{"uwuumad":[914],"uwauyydj":[57776],"uwros":[57781]},{"uwaeme":[5214],"uwaerne":[5763],"uway":[57781]},{"uwaeme":[5481,6321]},{"uwl":[1150],"uwaeme":[6034],"uwr":[57831]},{"uwnot":[1332],"uwe":[19301],"uwaekwe":[26325],"uwm":[58015]},{"uwr":[591],"uwins":[1437],"uwdibt":[1762],"uwaeme":[6582]},{"uwd":[1762]},{"uwi":[591],"uwe":[1762],"uwadiegwu":[36372],"uww3":[57776]},{"uwasi":[32538]},{"uwkr":[1700],"uwjr":[1762],"uwmlnj":[1762],"uwe":[36695]},{"uwum":[1791],"uwd":[1791],"uwer":[2303]},{"uwst":[2115],"uwen":[57964]},{"uwolniony":[1446],"uwe":[3619],"uwpx":[57781]},{"uwni":[940],"uwhgh":[1132],"uwnr":[1857],"uwea":[41069],"uwe":[41069]},{"uwb":[1760]},{"uwn":[1525],"uwt":[1760],"uwlij":[5779],"uwin":[57776]},{"uwayf":[3025],"uwe":[48371],"uwv":[57781],"uwcp":[57781],"uwfropmayuio":[58022]},{"uwu":[982],"uwe":[48477],"uwep":[57781]},{"uway":[1094],"uwl":[1137]},{"uwe":[1131],"uwvpspero":[1751],"uwrized":[2112]},{"uwe":[1020],"uwui":[1391],"uwrw":[1742],"uwim":[4253,4591,4954],"uwirokpitov":[57776],"uwotacrcropevoi":[57781],"uwocpepei":[57781],"uwopeveite":[57781]},{"uwe":[1015]},{"uwed":[870],"uwy":[1328],"uwntng":[1682],"uwl":[2113],"uwntal":[2120]},{"uwiirn":[957],"uweit":[57781],"uwl":[57826],"uwiiri":[58032]},{"uwn":[2115],"uwasi":[33003]},{"uwwro":[2161],"uwrd":[2161],"uwitfrtlic":[6850,7085],"uwe":[26302,34428,36090],"uwp":[57776]},{"uwifh":[843],"uwet":[1130],"uwd":[1132],"uwr":[1139],"uwe":[1789],"uwj":[5227,57911],"uwins":[36908],"uwphoto":[40001],"uwhjt":[57911],"uwi":[57950]}]