{
    "guid": "626807d8b685ba34416fb07e",
    "languageAgnosticNaturalKey": "pub-mwbv_202205_3_VIDEO",
    "naturalKey": "pub-mwbv_E_202205_3_VIDEO",
    "type": "video",
    "primaryCategory": "SeriesOrgAccomplishments",
    "description": "",
    "firstPublished": "2022-05-30T19:20:54.221Z",
    "duration": 482.219,
    "durationFormattedHHMM": "8:02",
    "durationFormattedMinSec": "8m 2s",
    "files": [
        {
            "progressiveDownloadURL": "https://download-a.akamaihd.net/files/media_periodical/b6/mwbv_E_202205_03_r240P.mp4",
            "checksum": "3ba80c86cfef16348b85f224a2d55e92",
            "filesize": 14908734,
            "modifiedDatetime": "2022-05-30T04:09:04.000Z",
            "bitRate": 241.5385631321039,
            "duration": 482.219,
            "frameHeight": 234,
            "frameWidth": 416,
            "label": "240p",
            "frameRate": 23.976,
            "mimetype": "video/mp4",
            "subtitled": false,
            "subtitles": {
                "url": "https://download-a.akamaihd.net/files/media_periodical/60/mwbv_E_202205_03.vtt",
                "modifiedDatetime": "2022-05-30T04:08:49.000Z",
                "checksum": "18fc0bcce3986593bbadf5a034639883"
            }
        },
        {
            "progressiveDownloadURL": "https://download-a.akamaihd.net/files/media_periodical/77/mwbv_E_202205_03_r360P.mp4",
            "checksum": "f9167e614c7a5adf4509c9b7663b93fa",
            "filesize": 28742240,
            "modifiedDatetime": "2022-05-30T04:09:02.000Z",
            "bitRate": 465.6774810347617,
            "duration": 482.198,
            "frameHeight": 360,
            "frameWidth": 640,
            "label": "360p",
            "frameRate": 23.976,
            "mimetype": "video/mp4",
            "subtitled": false,
            "subtitles": {
                "url": "https://download-a.akamaihd.net/files/media_periodical/60/mwbv_E_202205_03.vtt",
                "modifiedDatetime": "2022-05-30T04:08:49.000Z",
                "checksum": "18fc0bcce3986593bbadf5a034639883"
            }
        },
        {
            "progressiveDownloadURL": "https://download-a.akamaihd.net/files/media_periodical/a3/mwbv_E_202205_03_r480P.mp4",
            "checksum": "aa8e083660f6b1b6d494feaf4ee2a4d7",
            "filesize": 53198528,
            "modifiedDatetime": "2022-05-30T04:08:56.000Z",
            "bitRate": 861.9146076922758,
            "duration": 482.198,
            "frameHeight": 540,
            "frameWidth": 960,
            "label": "480p",
            "frameRate": 23.976,
            "mimetype": "video/mp4",
            "subtitled": false,
            "subtitles": {
                "url": "https://download-a.akamaihd.net/files/media_periodical/60/mwbv_E_202205_03.vtt",
                "modifiedDatetime": "2022-05-30T04:08:49.000Z",
                "checksum": "18fc0bcce3986593bbadf5a034639883"
            }
        },
        {
            "progressiveDownloadURL": "https://download-a.akamaihd.net/files/media_periodical/41/mwbv_E_202205_03_r720P.mp4",
            "checksum": "6e39d8256f41ef63189ef3e453b9e1fc",
            "filesize": 88826056,
            "modifiedDatetime": "2022-05-30T04:08:52.000Z",
            "bitRate": 1439.146496874728,
            "duration": 482.198,
            "frameHeight": 720,
            "frameWidth": 1280,
            "label": "720p",
            "frameRate": 23.976,
            "mimetype": "video/mp4",
            "subtitled": false,
            "subtitles": {
                "url": "https://download-a.akamaihd.net/files/media_periodical/60/mwbv_E_202205_03.vtt",
                "modifiedDatetime": "2022-05-30T04:08:49.000Z",
                "checksum": "18fc0bcce3986593bbadf5a034639883"
            }
        }
    ],
    "printReferences": [
        "mwbv.202205-3.v",
        "mwbv.202205-3"
    ],
    "subtitlesUrl": "https://download-a.akamaihd.net/files/media_periodical/60/mwbv_E_202205_03.vtt",
    "Name": "pub-mwbv_E_202205_3_VIDEO",
    "Title": "Organizational Accomplishments—Jehovah’s Love Touches Africa in a Special Way",
    "UndatedReferenceTitle": "Organizational Accomplishments—Jehovah’s Love Touches Africa in a Special Way",
    "ShortTitle": null,
    "Category": "vod",
    "Year": 2022,
    "Symbol": "SeriesOrgAccomplishments"
}